package_test/__init__.py
package_test/info.py
kavian_info-1.0.2.dist-info/LICENSE
kavian_info-1.0.2.dist-info/METADATA
kavian_info-1.0.2.dist-info/WHEEL
kavian_info-1.0.2.dist-info/entry_points.txt
kavian_info-1.0.2.dist-info/top_level.txt
kavian_info-1.0.2.dist-info/RECORD
