Metadata-Version: 2.1
Name: kavian-info
Version: 1.0.2
Summary: Gives you some info about Kavian
Author-email: Kavian <kavianam@gmail.com>
License: Copyright (c) 2018 The Python Packaging Authority        
Project-URL: Homepage, https://kavianam.ir/
Keywords: kavian,info,pattern matching
Classifier: License :: OSI Approved :: MIT License
Classifier: Programming Language :: Python
Classifier: Programming Language :: Python :: 3
Requires-Python: >=3.10
License-File: LICENSE
Requires-Dist: colorama (>=0.4.0)
